{
	"song": {
		"player1": "bf",
		"uiSkin": "default",
		"notes": [
			{
				"changeSignature": false,
				"numerator": 4,
				"altAnim": false,
				"mustHitSection": false,
				"lengthInSteps": 20,
				"typeOfSection": 0,
				"sectionNotes": [],
				"gfSection": false,
				"denominator": 4,
				"changeBPM": false,
				"bpm": 150
			},
			{
				"changeSignature": false,
				"numerator": 4,
				"altAnim": false,
				"mustHitSection": true,
				"lengthInSteps": 20,
				"typeOfSection": 0,
				"sectionNotes": [],
				"gfSection": false,
				"denominator": 4,
				"changeBPM": false,
				"bpm": 150
			},
			{
				"changeSignature": false,
				"numerator": 5,
				"altAnim": false,
				"mustHitSection": false,
				"lengthInSteps": 20,
				"typeOfSection": 0,
				"sectionNotes": [],
				"gfSection": false,
				"denominator": 4,
				"changeBPM": false,
				"bpm": 160
			},
			{
				"changeSignature": false,
				"numerator": 5,
				"altAnim": false,
				"mustHitSection": true,
				"lengthInSteps": 20,
				"typeOfSection": 0,
				"sectionNotes": [],
				"gfSection": false,
				"denominator": 4,
				"changeBPM": false,
				"bpm": 160
			},
			{
				"changeSignature": false,
				"numerator": 5,
				"altAnim": false,
				"mustHitSection": false,
				"lengthInSteps": 20,
				"typeOfSection": 0,
				"sectionNotes": [
					[
						7500,
						7,
						0,
						""
					],
					[
						7875,
						7,
						0,
						""
					],
					[
						8062.5,
						0,
						0,
						""
					],
					[
						8437.5,
						1,
						0,
						""
					],
					[
						8625,
						5,
						0,
						""
					],
					[
						9000,
						2,
						93.75,
						""
					]
				],
				"gfSection": false,
				"denominator": 4,
				"changeBPM": false,
				"bpm": 160
			},
			{
				"changeSignature": false,
				"numerator": 5,
				"altAnim": false,
				"mustHitSection": false,
				"lengthInSteps": 20,
				"typeOfSection": 0,
				"sectionNotes": [
					[
						10875,
						2,
						93.75,
						""
					],
					[
						9375,
						1,
						0,
						""
					],
					[
						9750,
						1,
						0,
						""
					],
					[
						9937.5,
						4,
						0,
						""
					],
					[
						10312.5,
						7,
						0,
						""
					],
					[
						10500,
						9,
						93.75,
						""
					]
				],
				"gfSection": false,
				"denominator": 4,
				"changeBPM": false,
				"bpm": 160
			},
			{
				"changeSignature": false,
				"numerator": 5,
				"altAnim": false,
				"mustHitSection": false,
				"lengthInSteps": 20,
				"typeOfSection": 0,
				"sectionNotes": [
					[
						11250,
						7,
						0,
						""
					],
					[
						11625,
						7,
						0,
						""
					],
					[
						11812.5,
						0,
						0,
						""
					],
					[
						12187.5,
						1,
						0,
						""
					],
					[
						12375,
						5,
						0,
						""
					],
					[
						12750,
						2,
						93.75,
						""
					]
				],
				"gfSection": false,
				"denominator": 4,
				"changeBPM": false,
				"bpm": 160
			},
			{
				"changeSignature": false,
				"numerator": 5,
				"altAnim": false,
				"mustHitSection": false,
				"lengthInSteps": 20,
				"typeOfSection": 0,
				"sectionNotes": [
					[
						13125,
						1,
						0,
						""
					],
					[
						13500,
						1,
						0,
						""
					],
					[
						13687.5,
						4,
						0,
						""
					],
					[
						14062.5,
						7,
						0,
						""
					],
					[
						14250,
						9,
						93.75,
						""
					],
					[
						14625,
						4,
						0,
						""
					],
					[
						14812.5,
						5,
						0,
						""
					]
				],
				"gfSection": false,
				"denominator": 4,
				"changeBPM": false,
				"bpm": 160
			},
			{
				"changeSignature": false,
				"numerator": 5,
				"altAnim": false,
				"mustHitSection": true,
				"lengthInSteps": 20,
				"typeOfSection": 0,
				"sectionNotes": [
					[
						15000,
						2,
						0,
						""
					],
					[
						15375,
						2,
						0,
						""
					],
					[
						15562.5,
						7,
						0,
						""
					],
					[
						15937.5,
						5,
						0,
						""
					],
					[
						16125,
						4,
						0,
						""
					],
					[
						16500,
						6,
						0,
						""
					]
				],
				"gfSection": false,
				"denominator": 4,
				"changeBPM": false,
				"bpm": 160
			},
			{
				"changeSignature": false,
				"numerator": 5,
				"altAnim": false,
				"mustHitSection": true,
				"lengthInSteps": 20,
				"typeOfSection": 0,
				"sectionNotes": [
					[
						16875,
						3,
						0,
						""
					],
					[
						17250,
						3,
						0,
						""
					],
					[
						17437.5,
						5,
						0,
						""
					],
					[
						17812.5,
						0,
						0,
						""
					],
					[
						17906.25,
						7,
						375,
						""
					],
					[
						18375,
						2,
						0,
						""
					]
				],
				"gfSection": false,
				"denominator": 4,
				"changeBPM": false,
				"bpm": 160
			},
			{
				"changeSignature": false,
				"numerator": 5,
				"altAnim": false,
				"mustHitSection": true,
				"lengthInSteps": 20,
				"typeOfSection": 0,
				"sectionNotes": [
					[
						19125,
						2,
						0,
						""
					],
					[
						19312.5,
						7,
						0,
						""
					],
					[
						19687.5,
						5,
						0,
						""
					],
					[
						19875,
						4,
						0,
						""
					],
					[
						20250,
						6,
						0,
						""
					],
					[
						18750,
						0,
						0,
						""
					]
				],
				"gfSection": false,
				"denominator": 4,
				"changeBPM": false,
				"bpm": 160
			},
			{
				"changeSignature": false,
				"numerator": 5,
				"altAnim": false,
				"mustHitSection": true,
				"lengthInSteps": 20,
				"typeOfSection": 0,
				"sectionNotes": [
					[
						20625,
						3,
						0,
						""
					],
					[
						21187.5,
						5,
						0,
						""
					],
					[
						21562.5,
						0,
						0,
						""
					],
					[
						21656.25,
						7,
						375,
						""
					],
					[
						22125,
						2,
						0,
						""
					],
					[
						21000,
						6,
						0,
						""
					],
					[
						22312.5,
						5,
						0,
						""
					]
				],
				"gfSection": false,
				"denominator": 4,
				"changeBPM": false,
				"bpm": 160
			},
			{
				"changeSignature": true,
				"numerator": 7,
				"altAnim": false,
				"mustHitSection": false,
				"lengthInSteps": 28,
				"typeOfSection": 0,
				"sectionNotes": [
					[
						22500,
						2,
						0,
						""
					],
					[
						22593.75,
						5,
						0,
						""
					],
					[
						22687.5,
						1,
						0,
						""
					],
					[
						22875,
						6,
						0,
						""
					],
					[
						23062.5,
						8,
						0,
						""
					],
					[
						23250,
						1,
						0,
						""
					],
					[
						23343.75,
						1,
						0,
						""
					],
					[
						23437.5,
						4,
						0,
						""
					],
					[
						23625,
						7,
						0,
						""
					],
					[
						23812.5,
						8,
						0,
						""
					],
					[
						24000,
						0,
						0,
						""
					],
					[
						24187.5,
						5,
						0,
						""
					],
					[
						24281.25,
						6,
						0,
						""
					],
					[
						24375,
						8,
						0,
						""
					],
					[
						24562.5,
						2,
						0,
						""
					],
					[
						24750,
						1,
						0,
						""
					],
					[
						24843.75,
						8,
						0,
						""
					],
					[
						24937.5,
						9,
						0,
						""
					]
				],
				"gfSection": false,
				"denominator": 4,
				"changeBPM": false,
				"bpm": 160
			},
			{
				"changeSignature": false,
				"numerator": 5,
				"altAnim": false,
				"mustHitSection": false,
				"lengthInSteps": 28,
				"typeOfSection": 0,
				"sectionNotes": [
					[
						25125,
						2,
						0,
						""
					],
					[
						25218.75,
						5,
						0,
						""
					],
					[
						25312.5,
						1,
						0,
						""
					],
					[
						25500,
						6,
						0,
						""
					],
					[
						25687.5,
						8,
						0,
						""
					],
					[
						25875,
						1,
						0,
						""
					],
					[
						25968.75,
						1,
						0,
						""
					],
					[
						26062.5,
						4,
						0,
						""
					],
					[
						26250,
						7,
						0,
						""
					],
					[
						26437.5,
						8,
						0,
						""
					],
					[
						26625,
						4,
						0,
						""
					],
					[
						26718.75,
						7,
						0,
						""
					],
					[
						26906.25,
						1,
						0,
						""
					],
					[
						26812.5,
						2,
						0,
						""
					],
					[
						27000,
						9,
						0,
						""
					],
					[
						27093.75,
						8,
						0,
						""
					],
					[
						27187.5,
						0,
						0,
						""
					],
					[
						27281.25,
						1,
						0,
						""
					],
					[
						27375,
						7,
						0,
						""
					],
					[
						27562.5,
						9,
						0,
						""
					]
				],
				"gfSection": false,
				"denominator": 4,
				"changeBPM": false,
				"bpm": 160
			},
			{
				"changeSignature": false,
				"numerator": 5,
				"altAnim": false,
				"mustHitSection": true,
				"lengthInSteps": 28,
				"typeOfSection": 0,
				"sectionNotes": [
					[
						27750,
						2,
						0,
						""
					],
					[
						27843.75,
						3,
						0,
						""
					],
					[
						27937.5,
						4,
						0,
						""
					],
					[
						28125,
						1,
						0,
						""
					],
					[
						28312.5,
						6,
						0,
						""
					],
					[
						28500,
						3,
						0,
						""
					],
					[
						28593.75,
						3,
						0,
						""
					],
					[
						28687.5,
						4,
						0,
						""
					],
					[
						28875,
						5,
						0,
						""
					],
					[
						29062.5,
						2,
						0,
						""
					],
					[
						29250,
						1,
						0,
						""
					],
					[
						29437.5,
						6,
						0,
						""
					],
					[
						29531.25,
						7,
						0,
						""
					],
					[
						29625,
						6,
						0,
						""
					],
					[
						29812.5,
						0,
						0,
						""
					],
					[
						30000,
						1,
						0,
						""
					],
					[
						30093.75,
						2,
						0,
						""
					],
					[
						30187.5,
						7,
						0,
						""
					]
				],
				"gfSection": false,
				"denominator": 4,
				"changeBPM": false,
				"bpm": 160
			},
			{
				"changeSignature": false,
				"numerator": 5,
				"altAnim": false,
				"mustHitSection": true,
				"lengthInSteps": 28,
				"typeOfSection": 0,
				"sectionNotes": [
					[
						30375,
						2,
						0,
						""
					],
					[
						30468.75,
						3,
						0,
						""
					],
					[
						30562.5,
						4,
						0,
						""
					],
					[
						30750,
						1,
						0,
						""
					],
					[
						30937.5,
						6,
						0,
						""
					],
					[
						31125,
						3,
						0,
						""
					],
					[
						31218.75,
						3,
						0,
						""
					],
					[
						31312.5,
						4,
						0,
						""
					],
					[
						31500,
						5,
						0,
						""
					],
					[
						31687.5,
						2,
						0,
						""
					],
					[
						31875,
						6,
						0,
						""
					],
					[
						31968.75,
						6,
						0,
						""
					],
					[
						32062.5,
						7,
						0,
						""
					],
					[
						32156.25,
						7,
						0,
						""
					],
					[
						32250,
						4,
						0,
						""
					],
					[
						32343.75,
						4,
						0,
						""
					],
					[
						32437.5,
						2,
						0,
						""
					],
					[
						32531.25,
						2,
						0,
						""
					],
					[
						32625,
						5,
						0,
						""
					],
					[
						32812.5,
						3,
						0,
						""
					]
				],
				"gfSection": false,
				"denominator": 4,
				"changeBPM": false,
				"bpm": 160
			},
			{
				"changeSignature": false,
				"numerator": 5,
				"altAnim": false,
				"mustHitSection": false,
				"lengthInSteps": 28,
				"typeOfSection": 0,
				"sectionNotes": [
					[
						33000,
						2,
						0,
						""
					],
					[
						33093.75,
						5,
						0,
						""
					],
					[
						33187.5,
						1,
						0,
						""
					],
					[
						33375,
						6,
						0,
						""
					],
					[
						33562.5,
						8,
						0,
						""
					],
					[
						33750,
						1,
						0,
						""
					],
					[
						33843.75,
						1,
						0,
						""
					],
					[
						33937.5,
						4,
						0,
						""
					],
					[
						34125,
						7,
						0,
						""
					],
					[
						34312.5,
						8,
						0,
						""
					],
					[
						34500,
						0,
						0,
						""
					],
					[
						34687.5,
						5,
						0,
						""
					],
					[
						34781.25,
						6,
						0,
						""
					],
					[
						34875,
						8,
						0,
						""
					],
					[
						35062.5,
						2,
						0,
						""
					],
					[
						35250,
						1,
						0,
						""
					],
					[
						35343.75,
						8,
						0,
						""
					],
					[
						35437.5,
						9,
						0,
						""
					],
					[
						33000,
						13,
						1406.25,
						""
					],
					[
						34500,
						15,
						468.75,
						""
					],
					[
						35062.5,
						16,
						468.75,
						""
					]
				],
				"gfSection": false,
				"denominator": 4,
				"changeBPM": false,
				"bpm": 160
			},
			{
				"changeSignature": false,
				"numerator": 5,
				"altAnim": false,
				"mustHitSection": false,
				"lengthInSteps": 28,
				"typeOfSection": 0,
				"sectionNotes": [
					[
						35625,
						2,
						0,
						""
					],
					[
						35718.75,
						5,
						0,
						""
					],
					[
						35812.5,
						1,
						0,
						""
					],
					[
						36000,
						6,
						0,
						""
					],
					[
						36187.5,
						8,
						0,
						""
					],
					[
						36375,
						1,
						0,
						""
					],
					[
						36468.75,
						1,
						0,
						""
					],
					[
						36562.5,
						4,
						0,
						""
					],
					[
						36750,
						7,
						0,
						""
					],
					[
						36937.5,
						8,
						0,
						""
					],
					[
						37125,
						4,
						0,
						""
					],
					[
						37218.75,
						7,
						0,
						""
					],
					[
						37406.25,
						1,
						0,
						""
					],
					[
						37312.5,
						2,
						0,
						""
					],
					[
						37500,
						9,
						0,
						""
					],
					[
						37593.75,
						8,
						0,
						""
					],
					[
						37687.5,
						0,
						0,
						""
					],
					[
						37781.25,
						1,
						0,
						""
					],
					[
						37875,
						7,
						0,
						""
					],
					[
						38062.5,
						9,
						0,
						""
					],
					[
						35625,
						10,
						1406.25,
						""
					],
					[
						37125,
						16,
						468.75,
						""
					],
					[
						37687.5,
						12,
						468.75,
						""
					]
				],
				"gfSection": false,
				"denominator": 4,
				"changeBPM": false,
				"bpm": 160
			},
			{
				"changeSignature": false,
				"numerator": 5,
				"altAnim": false,
				"mustHitSection": true,
				"lengthInSteps": 28,
				"typeOfSection": 0,
				"sectionNotes": [
					[
						38250,
						2,
						0,
						""
					],
					[
						38343.75,
						3,
						0,
						""
					],
					[
						38437.5,
						4,
						0,
						""
					],
					[
						38625,
						1,
						0,
						""
					],
					[
						38812.5,
						6,
						0,
						""
					],
					[
						39000,
						3,
						0,
						""
					],
					[
						39093.75,
						3,
						0,
						""
					],
					[
						39187.5,
						4,
						0,
						""
					],
					[
						39375,
						5,
						0,
						""
					],
					[
						39562.5,
						2,
						0,
						""
					],
					[
						39750,
						1,
						0,
						""
					],
					[
						39937.5,
						6,
						0,
						""
					],
					[
						40031.25,
						7,
						0,
						""
					],
					[
						40125,
						6,
						0,
						""
					],
					[
						40312.5,
						0,
						0,
						""
					],
					[
						40500,
						1,
						0,
						""
					],
					[
						40593.75,
						2,
						0,
						""
					],
					[
						40687.5,
						7,
						0,
						""
					],
					[
						38250,
						12,
						1406.25,
						""
					],
					[
						39750,
						15,
						468.75,
						""
					],
					[
						40312.5,
						17,
						468.75,
						""
					]
				],
				"gfSection": false,
				"denominator": 4,
				"changeBPM": false,
				"bpm": 160
			},
			{
				"changeSignature": false,
				"numerator": 5,
				"altAnim": false,
				"mustHitSection": true,
				"lengthInSteps": 28,
				"typeOfSection": 0,
				"sectionNotes": [
					[
						40875,
						2,
						0,
						""
					],
					[
						40968.75,
						3,
						0,
						""
					],
					[
						41062.5,
						4,
						0,
						""
					],
					[
						41250,
						1,
						0,
						""
					],
					[
						41437.5,
						6,
						0,
						""
					],
					[
						41625,
						3,
						0,
						""
					],
					[
						41718.75,
						3,
						0,
						""
					],
					[
						41812.5,
						4,
						0,
						""
					],
					[
						42000,
						5,
						0,
						""
					],
					[
						42187.5,
						2,
						0,
						""
					],
					[
						42375,
						6,
						0,
						""
					],
					[
						42468.75,
						6,
						0,
						""
					],
					[
						42562.5,
						7,
						0,
						""
					],
					[
						42656.25,
						7,
						0,
						""
					],
					[
						42750,
						4,
						0,
						""
					],
					[
						42843.75,
						4,
						0,
						""
					],
					[
						42937.5,
						2,
						0,
						""
					],
					[
						43031.25,
						2,
						0,
						""
					],
					[
						43125,
						5,
						0,
						""
					],
					[
						43312.5,
						3,
						0,
						""
					],
					[
						40875,
						14,
						1406.25,
						""
					],
					[
						42375,
						10,
						468.75,
						""
					],
					[
						42937.5,
						13,
						468.75,
						""
					]
				],
				"gfSection": false,
				"denominator": 4,
				"changeBPM": false,
				"bpm": 160
			},
			{
				"changeSignature": true,
				"numerator": 11,
				"altAnim": false,
				"mustHitSection": false,
				"lengthInSteps": 44,
				"typeOfSection": 0,
				"sectionNotes": [
					[
						43687.5,
						7,
						0,
						""
					],
					[
						43781.25,
						7,
						0,
						""
					],
					[
						43875,
						7,
						0,
						""
					],
					[
						43500,
						4,
						0,
						""
					],
					[
						44062.5,
						8,
						0,
						""
					],
					[
						44437.5,
						9,
						0,
						""
					],
					[
						44625,
						1,
						140.625,
						""
					],
					[
						44250,
						1,
						140.625,
						""
					],
					[
						44812.5,
						5,
						0,
						""
					],
					[
						45000,
						7,
						0,
						""
					],
					[
						45187.5,
						2,
						0,
						""
					],
					[
						45375,
						0,
						0,
						""
					]
				],
				"gfSection": false,
				"denominator": 8,
				"changeBPM": false,
				"bpm": 160
			},
			{
				"changeSignature": false,
				"numerator": 5,
				"altAnim": false,
				"mustHitSection": false,
				"lengthInSteps": 44,
				"typeOfSection": 0,
				"sectionNotes": [
					[
						45750,
						7,
						0,
						""
					],
					[
						45843.75,
						7,
						0,
						""
					],
					[
						45937.5,
						7,
						0,
						""
					],
					[
						45562.5,
						4,
						0,
						""
					],
					[
						46125,
						8,
						0,
						""
					],
					[
						46500,
						9,
						0,
						""
					],
					[
						46687.5,
						1,
						140.625,
						""
					],
					[
						46312.5,
						1,
						140.625,
						""
					],
					[
						47062.5,
						7,
						0,
						""
					],
					[
						47250,
						2,
						0,
						""
					],
					[
						47437.5,
						0,
						0,
						""
					],
					[
						46875,
						2,
						0,
						""
					],
					[
						46968.75,
						5,
						0,
						""
					]
				],
				"gfSection": false,
				"denominator": 4,
				"changeBPM": false,
				"bpm": 160
			},
			{
				"changeSignature": false,
				"numerator": 5,
				"altAnim": false,
				"mustHitSection": false,
				"lengthInSteps": 44,
				"typeOfSection": 0,
				"sectionNotes": [
					[
						47812.5,
						7,
						0,
						""
					],
					[
						47906.25,
						7,
						0,
						""
					],
					[
						48000,
						7,
						0,
						""
					],
					[
						47625,
						4,
						0,
						""
					],
					[
						48187.5,
						8,
						0,
						""
					],
					[
						48562.5,
						9,
						0,
						""
					],
					[
						48750,
						1,
						140.625,
						""
					],
					[
						48375,
						1,
						140.625,
						""
					],
					[
						48937.5,
						5,
						0,
						""
					],
					[
						49125,
						7,
						0,
						""
					],
					[
						49312.5,
						2,
						0,
						""
					],
					[
						49500,
						0,
						0,
						""
					],
					[
						47625,
						0,
						0,
						""
					],
					[
						47812.5,
						2,
						0,
						""
					],
					[
						47906.25,
						3,
						0,
						""
					],
					[
						48000,
						2,
						0,
						""
					],
					[
						48187.5,
						4,
						0,
						""
					],
					[
						48375,
						9,
						140.625,
						""
					],
					[
						48562.5,
						2,
						0,
						""
					],
					[
						48750,
						6,
						140.625,
						""
					],
					[
						48937.5,
						0,
						0,
						""
					],
					[
						49125,
						2,
						0,
						""
					],
					[
						49312.5,
						9,
						0,
						""
					],
					[
						49500,
						7,
						0,
						""
					]
				],
				"gfSection": false,
				"denominator": 4,
				"changeBPM": false,
				"bpm": 160
			},
			{
				"changeSignature": false,
				"numerator": 5,
				"altAnim": false,
				"mustHitSection": false,
				"lengthInSteps": 44,
				"typeOfSection": 0,
				"sectionNotes": [
					[
						49875,
						7,
						0,
						""
					],
					[
						49968.75,
						7,
						0,
						""
					],
					[
						50062.5,
						7,
						0,
						""
					],
					[
						49687.5,
						4,
						0,
						""
					],
					[
						50250,
						8,
						0,
						""
					],
					[
						50625,
						9,
						0,
						""
					],
					[
						50812.5,
						1,
						140.625,
						""
					],
					[
						50437.5,
						1,
						140.625,
						""
					],
					[
						51187.5,
						7,
						0,
						""
					],
					[
						51375,
						2,
						0,
						""
					],
					[
						51562.5,
						0,
						0,
						""
					],
					[
						51000,
						2,
						0,
						""
					],
					[
						51093.75,
						5,
						0,
						""
					],
					[
						49687.5,
						9,
						0,
						""
					],
					[
						49875,
						8,
						0,
						""
					],
					[
						49968.75,
						4,
						0,
						""
					],
					[
						50062.5,
						8,
						0,
						""
					],
					[
						50250,
						9,
						0,
						""
					],
					[
						50437.5,
						4,
						140.625,
						""
					],
					[
						50625,
						6,
						0,
						""
					],
					[
						50812.5,
						6,
						140.625,
						""
					],
					[
						51000,
						4,
						0,
						""
					],
					[
						51093.75,
						8,
						0,
						""
					],
					[
						51187.5,
						1,
						0,
						""
					],
					[
						51375,
						8,
						0,
						""
					],
					[
						51562.5,
						9,
						0,
						""
					]
				],
				"gfSection": false,
				"denominator": 4,
				"changeBPM": false,
				"bpm": 160
			},
			{
				"changeSignature": false,
				"numerator": 5,
				"altAnim": false,
				"mustHitSection": true,
				"lengthInSteps": 44,
				"typeOfSection": 0,
				"sectionNotes": [
					[
						51750,
						1,
						0,
						""
					],
					[
						51937.5,
						7,
						0,
						""
					],
					[
						52031.25,
						5,
						0,
						""
					],
					[
						52125,
						6,
						0,
						""
					],
					[
						52312.5,
						1,
						0,
						""
					],
					[
						52500,
						2,
						0,
						""
					],
					[
						52687.5,
						5,
						0,
						""
					],
					[
						52875,
						2,
						0,
						""
					],
					[
						53062.5,
						5,
						0,
						""
					],
					[
						53250,
						7,
						0,
						""
					],
					[
						53437.5,
						0,
						0,
						""
					],
					[
						53625,
						5,
						0,
						""
					]
				],
				"gfSection": false,
				"denominator": 4,
				"changeBPM": false,
				"bpm": 160
			},
			{
				"changeSignature": false,
				"numerator": 5,
				"altAnim": false,
				"mustHitSection": true,
				"lengthInSteps": 44,
				"typeOfSection": 0,
				"sectionNotes": [
					[
						53812.5,
						1,
						0,
						""
					],
					[
						54000,
						7,
						0,
						""
					],
					[
						54093.75,
						5,
						0,
						""
					],
					[
						54187.5,
						6,
						0,
						""
					],
					[
						54375,
						1,
						0,
						""
					],
					[
						54562.5,
						2,
						0,
						""
					],
					[
						54750,
						5,
						0,
						""
					],
					[
						55125,
						5,
						0,
						""
					],
					[
						55312.5,
						7,
						0,
						""
					],
					[
						55500,
						0,
						0,
						""
					],
					[
						55218.75,
						1,
						0,
						""
					],
					[
						54937.5,
						3,
						0,
						""
					],
					[
						55687.5,
						1,
						0,
						""
					]
				],
				"gfSection": false,
				"denominator": 4,
				"changeBPM": false,
				"bpm": 160
			},
			{
				"changeSignature": false,
				"numerator": 5,
				"altAnim": false,
				"mustHitSection": true,
				"lengthInSteps": 44,
				"typeOfSection": 0,
				"sectionNotes": [
					[
						55875,
						1,
						0,
						""
					],
					[
						56062.5,
						7,
						0,
						""
					],
					[
						56156.25,
						5,
						0,
						""
					],
					[
						56250,
						6,
						0,
						""
					],
					[
						56437.5,
						1,
						0,
						""
					],
					[
						56625,
						2,
						0,
						""
					],
					[
						56812.5,
						5,
						0,
						""
					],
					[
						57000,
						2,
						0,
						""
					],
					[
						57187.5,
						5,
						0,
						""
					],
					[
						57375,
						7,
						0,
						""
					],
					[
						57750,
						5,
						0,
						""
					],
					[
						55875,
						5,
						0,
						""
					],
					[
						56062.5,
						3,
						0,
						""
					],
					[
						56156.25,
						1,
						0,
						""
					],
					[
						56250,
						2,
						0,
						""
					],
					[
						56437.5,
						5,
						0,
						""
					],
					[
						56625,
						6,
						0,
						""
					],
					[
						56812.5,
						1,
						0,
						""
					],
					[
						57000,
						6,
						0,
						""
					],
					[
						57187.5,
						1,
						0,
						""
					],
					[
						57562.5,
						7,
						0,
						""
					],
					[
						57750,
						1,
						0,
						""
					],
					[
						57375,
						3,
						0,
						""
					],
					[
						57562.5,
						3,
						0,
						""
					]
				],
				"gfSection": false,
				"denominator": 4,
				"changeBPM": false,
				"bpm": 160
			},
			{
				"changeSignature": false,
				"numerator": 5,
				"altAnim": false,
				"mustHitSection": true,
				"lengthInSteps": 44,
				"typeOfSection": 0,
				"sectionNotes": [
					[
						57937.5,
						1,
						0,
						""
					],
					[
						58125,
						7,
						0,
						""
					],
					[
						58218.75,
						5,
						0,
						""
					],
					[
						58312.5,
						6,
						0,
						""
					],
					[
						58500,
						1,
						0,
						""
					],
					[
						58687.5,
						2,
						0,
						""
					],
					[
						58875,
						5,
						0,
						""
					],
					[
						59250,
						5,
						0,
						""
					],
					[
						59437.5,
						7,
						0,
						""
					],
					[
						59625,
						0,
						0,
						""
					],
					[
						59062.5,
						3,
						0,
						""
					],
					[
						59812.5,
						1,
						0,
						""
					],
					[
						57937.5,
						5,
						0,
						""
					],
					[
						58125,
						0,
						0,
						""
					],
					[
						58218.75,
						1,
						0,
						""
					],
					[
						58312.5,
						2,
						0,
						""
					],
					[
						58500,
						5,
						0,
						""
					],
					[
						58687.5,
						6,
						0,
						""
					],
					[
						58875,
						1,
						0,
						""
					],
					[
						59062.5,
						7,
						0,
						""
					],
					[
						59250,
						1,
						0,
						""
					],
					[
						59343.75,
						2,
						0,
						""
					],
					[
						59343.75,
						6,
						0,
						""
					],
					[
						59437.5,
						3,
						0,
						""
					],
					[
						59625,
						4,
						0,
						""
					],
					[
						59812.5,
						5,
						0,
						""
					]
				],
				"gfSection": false,
				"denominator": 4,
				"changeBPM": false,
				"bpm": 160
			},
			{
				"changeSignature": true,
				"numerator": 6,
				"altAnim": false,
				"mustHitSection": false,
				"lengthInSteps": 24,
				"typeOfSection": 0,
				"sectionNotes": [
					[
						60000,
						2,
						0,
						""
					],
					[
						60187.5,
						5,
						0,
						""
					],
					[
						60375,
						4,
						0,
						""
					],
					[
						60562.5,
						8,
						0,
						""
					],
					[
						60750,
						9,
						0,
						""
					],
					[
						60937.5,
						2,
						0,
						""
					],
					[
						60984.375,
						4,
						0,
						""
					],
					[
						61031.25,
						6,
						0,
						""
					]
				],
				"gfSection": false,
				"denominator": 8,
				"changeBPM": false,
				"bpm": 160
			},
			{
				"changeSignature": false,
				"numerator": 5,
				"altAnim": false,
				"mustHitSection": false,
				"lengthInSteps": 24,
				"typeOfSection": 0,
				"sectionNotes": [
					[
						61125,
						6,
						0,
						""
					],
					[
						61312.5,
						8,
						0,
						""
					],
					[
						61500,
						6,
						0,
						""
					],
					[
						61687.5,
						1,
						0,
						""
					],
					[
						61875,
						5,
						0,
						""
					],
					[
						62062.5,
						0,
						0,
						""
					]
				],
				"gfSection": false,
				"denominator": 4,
				"changeBPM": false,
				"bpm": 160
			},
			{
				"changeSignature": false,
				"numerator": 5,
				"altAnim": false,
				"mustHitSection": false,
				"lengthInSteps": 24,
				"typeOfSection": 0,
				"sectionNotes": [
					[
						62250,
						5,
						0,
						""
					],
					[
						62437.5,
						1,
						0,
						""
					],
					[
						62625,
						1,
						0,
						""
					],
					[
						62812.5,
						8,
						0,
						""
					],
					[
						63000,
						9,
						0,
						""
					],
					[
						63187.5,
						4,
						0,
						""
					],
					[
						63234.375,
						6,
						0,
						""
					],
					[
						63281.25,
						0,
						0,
						""
					]
				],
				"gfSection": false,
				"denominator": 4,
				"changeBPM": false,
				"bpm": 160
			},
			{
				"changeSignature": false,
				"numerator": 5,
				"altAnim": false,
				"mustHitSection": false,
				"lengthInSteps": 24,
				"typeOfSection": 0,
				"sectionNotes": [
					[
						63375,
						8,
						0,
						""
					],
					[
						63562.5,
						9,
						0,
						""
					],
					[
						63750,
						3,
						0,
						""
					],
					[
						63937.5,
						4,
						0,
						""
					],
					[
						64125,
						7,
						0,
						""
					],
					[
						64312.5,
						8,
						0,
						""
					]
				],
				"gfSection": false,
				"denominator": 4,
				"changeBPM": false,
				"bpm": 160
			},
			{
				"changeSignature": false,
				"numerator": 5,
				"altAnim": false,
				"mustHitSection": false,
				"lengthInSteps": 24,
				"typeOfSection": 0,
				"sectionNotes": [
					[
						64500,
						1,
						0,
						""
					],
					[
						64687.5,
						8,
						0,
						""
					],
					[
						64875,
						3,
						0,
						""
					],
					[
						65062.5,
						8,
						0,
						""
					],
					[
						65250,
						5,
						0,
						""
					],
					[
						65437.5,
						8,
						0,
						""
					],
					[
						65484.375,
						1,
						0,
						""
					],
					[
						65531.25,
						4,
						0,
						""
					]
				],
				"gfSection": false,
				"denominator": 4,
				"changeBPM": false,
				"bpm": 160
			},
			{
				"changeSignature": false,
				"numerator": 5,
				"altAnim": false,
				"mustHitSection": false,
				"lengthInSteps": 24,
				"typeOfSection": 0,
				"sectionNotes": [
					[
						65625,
						2,
						0,
						""
					],
					[
						65812.5,
						7,
						0,
						""
					],
					[
						66000,
						6,
						0,
						""
					],
					[
						66187.5,
						9,
						0,
						""
					],
					[
						66375,
						3,
						0,
						""
					],
					[
						66562.5,
						4,
						0,
						""
					]
				],
				"gfSection": false,
				"denominator": 4,
				"changeBPM": false,
				"bpm": 160
			},
			{
				"changeSignature": false,
				"numerator": 5,
				"altAnim": false,
				"mustHitSection": false,
				"lengthInSteps": 24,
				"typeOfSection": 0,
				"sectionNotes": [
					[
						66750,
						8,
						0,
						""
					],
					[
						66937.5,
						0,
						0,
						""
					],
					[
						67125,
						1,
						0,
						""
					],
					[
						67312.5,
						8,
						0,
						""
					],
					[
						67500,
						9,
						0,
						""
					],
					[
						67687.5,
						7,
						0,
						""
					]
				],
				"gfSection": false,
				"denominator": 4,
				"changeBPM": false,
				"bpm": 160
			},
			{
				"changeSignature": false,
				"numerator": 5,
				"altAnim": false,
				"mustHitSection": false,
				"lengthInSteps": 24,
				"typeOfSection": 0,
				"sectionNotes": [
					[
						67875,
						8,
						0,
						""
					],
					[
						68062.5,
						0,
						0,
						""
					],
					[
						68250,
						1,
						0,
						""
					],
					[
						68437.5,
						8,
						0,
						""
					],
					[
						68625,
						9,
						0,
						""
					],
					[
						68812.5,
						7,
						0,
						""
					]
				],
				"gfSection": false,
				"denominator": 4,
				"changeBPM": false,
				"bpm": 160
			},
			{
				"changeSignature": false,
				"numerator": 5,
				"altAnim": false,
				"mustHitSection": true,
				"lengthInSteps": 24,
				"typeOfSection": 0,
				"sectionNotes": [
					[
						69000,
						7,
						0,
						""
					],
					[
						69187.5,
						5,
						0,
						""
					],
					[
						69375,
						6,
						0,
						""
					],
					[
						69562.5,
						3,
						0,
						""
					],
					[
						69750,
						4,
						0,
						""
					],
					[
						69937.5,
						2,
						0,
						""
					],
					[
						69984.375,
						3,
						0,
						""
					],
					[
						70031.25,
						1,
						0,
						""
					]
				],
				"gfSection": false,
				"denominator": 4,
				"changeBPM": false,
				"bpm": 160
			},
			{
				"changeSignature": false,
				"numerator": 5,
				"altAnim": false,
				"mustHitSection": true,
				"lengthInSteps": 24,
				"typeOfSection": 0,
				"sectionNotes": [
					[
						70125,
						0,
						0,
						""
					],
					[
						70312.5,
						3,
						0,
						""
					],
					[
						70500,
						7,
						0,
						""
					],
					[
						70687.5,
						6,
						0,
						""
					],
					[
						70875,
						1,
						0,
						""
					],
					[
						71062.5,
						5,
						0,
						""
					]
				],
				"gfSection": false,
				"denominator": 4,
				"changeBPM": false,
				"bpm": 160
			},
			{
				"changeSignature": false,
				"numerator": 5,
				"altAnim": false,
				"mustHitSection": true,
				"lengthInSteps": 24,
				"typeOfSection": 0,
				"sectionNotes": [
					[
						71250,
						1,
						0,
						""
					],
					[
						71437.5,
						6,
						0,
						""
					],
					[
						71625,
						3,
						0,
						""
					],
					[
						71812.5,
						4,
						0,
						""
					],
					[
						72000,
						5,
						0,
						""
					],
					[
						72187.5,
						6,
						0,
						""
					],
					[
						72234.375,
						7,
						0,
						""
					],
					[
						72281.25,
						5,
						0,
						""
					]
				],
				"gfSection": false,
				"denominator": 4,
				"changeBPM": false,
				"bpm": 160
			},
			{
				"changeSignature": false,
				"numerator": 5,
				"altAnim": false,
				"mustHitSection": true,
				"lengthInSteps": 24,
				"typeOfSection": 0,
				"sectionNotes": [
					[
						72375,
						1,
						0,
						""
					],
					[
						72562.5,
						4,
						0,
						""
					],
					[
						72750,
						0,
						0,
						""
					],
					[
						72937.5,
						6,
						0,
						""
					],
					[
						73125,
						0,
						0,
						""
					],
					[
						73312.5,
						0,
						0,
						""
					]
				],
				"gfSection": false,
				"denominator": 4,
				"changeBPM": false,
				"bpm": 160
			},
			{
				"changeSignature": false,
				"numerator": 5,
				"altAnim": false,
				"mustHitSection": true,
				"lengthInSteps": 24,
				"typeOfSection": 0,
				"sectionNotes": [
					[
						73500,
						4,
						0,
						""
					],
					[
						73687.5,
						5,
						0,
						""
					],
					[
						73875,
						7,
						0,
						""
					],
					[
						74062.5,
						6,
						0,
						""
					],
					[
						74250,
						1,
						0,
						""
					],
					[
						74437.5,
						5,
						0,
						""
					],
					[
						74484.375,
						4,
						0,
						""
					],
					[
						74531.25,
						3,
						0,
						""
					]
				],
				"gfSection": false,
				"denominator": 4,
				"changeBPM": false,
				"bpm": 160
			},
			{
				"changeSignature": false,
				"numerator": 5,
				"altAnim": false,
				"mustHitSection": true,
				"lengthInSteps": 24,
				"typeOfSection": 0,
				"sectionNotes": [
					[
						74625,
						0,
						0,
						""
					],
					[
						74812.5,
						2,
						0,
						""
					],
					[
						75000,
						2,
						0,
						""
					],
					[
						75187.5,
						5,
						0,
						""
					],
					[
						75375,
						3,
						0,
						""
					],
					[
						75562.5,
						7,
						0,
						""
					]
				],
				"gfSection": false,
				"denominator": 4,
				"changeBPM": false,
				"bpm": 160
			},
			{
				"changeSignature": false,
				"numerator": 5,
				"altAnim": false,
				"mustHitSection": true,
				"lengthInSteps": 24,
				"typeOfSection": 0,
				"sectionNotes": [
					[
						75750,
						2,
						0,
						""
					],
					[
						75937.5,
						3,
						0,
						""
					],
					[
						76125,
						1,
						0,
						""
					],
					[
						76312.5,
						6,
						0,
						""
					],
					[
						76500,
						3,
						0,
						""
					],
					[
						76687.5,
						1,
						0,
						""
					]
				],
				"gfSection": false,
				"denominator": 4,
				"changeBPM": false,
				"bpm": 160
			},
			{
				"changeSignature": false,
				"numerator": 5,
				"altAnim": false,
				"mustHitSection": true,
				"lengthInSteps": 24,
				"typeOfSection": 0,
				"sectionNotes": [
					[
						76875,
						6,
						0,
						""
					],
					[
						77062.5,
						1,
						0,
						""
					],
					[
						77250,
						7,
						0,
						""
					],
					[
						77437.5,
						6,
						0,
						""
					],
					[
						77625,
						3,
						0,
						""
					],
					[
						77812.5,
						0,
						0,
						""
					]
				],
				"gfSection": false,
				"denominator": 4,
				"changeBPM": false,
				"bpm": 160
			},
			{
				"changeSignature": true,
				"numerator": 9,
				"altAnim": false,
				"mustHitSection": false,
				"lengthInSteps": 36,
				"typeOfSection": 0,
				"sectionNotes": [
					[
						78000,
						1,
						140.625,
						""
					],
					[
						78375,
						1,
						0,
						""
					],
					[
						78562.5,
						9,
						0,
						""
					],
					[
						78750,
						1,
						0,
						""
					],
					[
						78937.5,
						4,
						0,
						""
					],
					[
						79125,
						8,
						0,
						""
					],
					[
						79312.5,
						9,
						0,
						""
					],
					[
						79500,
						7,
						0,
						""
					]
				],
				"gfSection": false,
				"denominator": 8,
				"changeBPM": false,
				"bpm": 160
			},
			{
				"changeSignature": false,
				"numerator": 5,
				"altAnim": false,
				"mustHitSection": false,
				"lengthInSteps": 36,
				"typeOfSection": 0,
				"sectionNotes": [
					[
						79687.5,
						1,
						140.625,
						""
					],
					[
						80062.5,
						1,
						0,
						""
					],
					[
						80250,
						9,
						0,
						""
					],
					[
						80437.5,
						1,
						0,
						""
					],
					[
						81000,
						9,
						0,
						""
					],
					[
						80625,
						8,
						0,
						""
					],
					[
						80812.5,
						0,
						0,
						""
					],
					[
						81187.5,
						2,
						0,
						""
					]
				],
				"gfSection": false,
				"denominator": 4,
				"changeBPM": false,
				"bpm": 160
			},
			{
				"changeSignature": false,
				"numerator": 5,
				"altAnim": false,
				"mustHitSection": false,
				"lengthInSteps": 36,
				"typeOfSection": 0,
				"sectionNotes": [
					[
						81375,
						1,
						140.625,
						""
					],
					[
						81750,
						1,
						0,
						""
					],
					[
						81937.5,
						9,
						0,
						""
					],
					[
						82125,
						1,
						0,
						""
					],
					[
						82312.5,
						4,
						0,
						""
					],
					[
						82500,
						8,
						0,
						""
					],
					[
						82687.5,
						9,
						0,
						""
					],
					[
						82875,
						7,
						0,
						""
					]
				],
				"gfSection": false,
				"denominator": 4,
				"changeBPM": false,
				"bpm": 160
			},
			{
				"changeSignature": false,
				"numerator": 5,
				"altAnim": false,
				"mustHitSection": false,
				"lengthInSteps": 36,
				"typeOfSection": 0,
				"sectionNotes": [
					[
						83437.5,
						1,
						0,
						""
					],
					[
						83625,
						9,
						0,
						""
					],
					[
						83812.5,
						1,
						0,
						""
					],
					[
						84375,
						9,
						0,
						""
					],
					[
						84000,
						8,
						0,
						""
					],
					[
						84187.5,
						0,
						0,
						""
					],
					[
						84562.5,
						2,
						0,
						""
					],
					[
						83062.5,
						7,
						140.625,
						""
					]
				],
				"gfSection": false,
				"denominator": 4,
				"changeBPM": false,
				"bpm": 160
			},
			{
				"changeSignature": false,
				"numerator": 5,
				"altAnim": false,
				"mustHitSection": true,
				"lengthInSteps": 36,
				"typeOfSection": 0,
				"sectionNotes": [
					[
						84750,
						1,
						0,
						""
					],
					[
						85125,
						5,
						0,
						""
					],
					[
						85312.5,
						7,
						0,
						""
					],
					[
						85500,
						0,
						0,
						""
					],
					[
						85687.5,
						6,
						0,
						""
					],
					[
						85875,
						3,
						0,
						""
					],
					[
						86062.5,
						4,
						0,
						""
					],
					[
						86250,
						5,
						0,
						""
					]
				],
				"gfSection": false,
				"denominator": 4,
				"changeBPM": false,
				"bpm": 160
			},
			{
				"changeSignature": false,
				"numerator": 5,
				"altAnim": false,
				"mustHitSection": true,
				"lengthInSteps": 36,
				"typeOfSection": 0,
				"sectionNotes": [
					[
						86437.5,
						0,
						0,
						""
					],
					[
						86812.5,
						0,
						0,
						""
					],
					[
						87000,
						5,
						0,
						""
					],
					[
						87187.5,
						7,
						0,
						""
					],
					[
						87375,
						2,
						0,
						""
					],
					[
						87562.5,
						6,
						0,
						""
					],
					[
						87750,
						5,
						0,
						""
					],
					[
						87937.5,
						3,
						0,
						""
					]
				],
				"gfSection": false,
				"denominator": 4,
				"changeBPM": false,
				"bpm": 160
			},
			{
				"changeSignature": false,
				"numerator": 5,
				"altAnim": false,
				"mustHitSection": true,
				"lengthInSteps": 36,
				"typeOfSection": 0,
				"sectionNotes": [
					[
						88125,
						1,
						0,
						""
					],
					[
						88500,
						5,
						0,
						""
					],
					[
						88687.5,
						7,
						0,
						""
					],
					[
						88875,
						0,
						0,
						""
					],
					[
						89062.5,
						6,
						0,
						""
					],
					[
						89250,
						3,
						0,
						""
					],
					[
						89437.5,
						4,
						0,
						""
					],
					[
						89625,
						5,
						0,
						""
					]
				],
				"gfSection": false,
				"denominator": 4,
				"changeBPM": false,
				"bpm": 160
			},
			{
				"changeSignature": false,
				"numerator": 5,
				"altAnim": false,
				"mustHitSection": true,
				"lengthInSteps": 36,
				"typeOfSection": 0,
				"sectionNotes": [
					[
						90937.5,
						6,
						0,
						""
					],
					[
						91125,
						5,
						0,
						""
					],
					[
						89812.5,
						1,
						0,
						""
					],
					[
						90187.5,
						6,
						0,
						""
					],
					[
						90375,
						5,
						0,
						""
					],
					[
						90562.5,
						2,
						0,
						""
					],
					[
						90750,
						3,
						0,
						""
					],
					[
						91312.5,
						0,
						0,
						""
					]
				],
				"gfSection": false,
				"denominator": 4,
				"changeBPM": false,
				"bpm": 160
			},
			{
				"changeSignature": false,
				"numerator": 5,
				"altAnim": false,
				"mustHitSection": false,
				"lengthInSteps": 36,
				"typeOfSection": 0,
				"sectionNotes": [
					[
						91500,
						2,
						0,
						""
					],
					[
						91875,
						9,
						0,
						""
					],
					[
						92250,
						0,
						0,
						""
					],
					[
						92437.5,
						1,
						0,
						""
					],
					[
						92625,
						8,
						0,
						""
					],
					[
						92812.5,
						4,
						0,
						""
					],
					[
						93000,
						5,
						0,
						""
					],
					[
						92343.75,
						9,
						0,
						""
					]
				],
				"gfSection": false,
				"denominator": 4,
				"changeBPM": false,
				"bpm": 160
			},
			{
				"changeSignature": false,
				"numerator": 5,
				"altAnim": false,
				"mustHitSection": false,
				"lengthInSteps": 36,
				"typeOfSection": 0,
				"sectionNotes": [
					[
						93187.5,
						2,
						0,
						""
					],
					[
						93562.5,
						9,
						0,
						""
					],
					[
						93937.5,
						0,
						0,
						""
					],
					[
						94031.25,
						3,
						0,
						""
					],
					[
						94125,
						7,
						0,
						""
					],
					[
						94312.5,
						4,
						0,
						""
					],
					[
						94500,
						8,
						0,
						""
					],
					[
						94687.5,
						2,
						0,
						""
					]
				],
				"gfSection": false,
				"denominator": 4,
				"changeBPM": false,
				"bpm": 160
			},
			{
				"changeSignature": false,
				"numerator": 5,
				"altAnim": false,
				"mustHitSection": false,
				"lengthInSteps": 36,
				"typeOfSection": 0,
				"sectionNotes": [
					[
						94875,
						2,
						0,
						""
					],
					[
						95250,
						9,
						0,
						""
					],
					[
						95625,
						0,
						0,
						""
					],
					[
						95812.5,
						1,
						0,
						""
					],
					[
						96000,
						8,
						0,
						""
					],
					[
						96187.5,
						4,
						0,
						""
					],
					[
						96375,
						5,
						0,
						""
					],
					[
						95718.75,
						9,
						0,
						""
					],
					[
						94875,
						8,
						0,
						""
					],
					[
						95250,
						3,
						0,
						""
					],
					[
						95625,
						4,
						0,
						""
					],
					[
						95718.75,
						3,
						0,
						""
					],
					[
						95812.5,
						7,
						0,
						""
					],
					[
						96000,
						2,
						0,
						""
					],
					[
						96187.5,
						6,
						0,
						""
					],
					[
						96375,
						9,
						0,
						""
					]
				],
				"gfSection": false,
				"denominator": 4,
				"changeBPM": false,
				"bpm": 160
			},
			{
				"changeSignature": false,
				"numerator": 5,
				"altAnim": false,
				"mustHitSection": false,
				"lengthInSteps": 36,
				"typeOfSection": 0,
				"sectionNotes": [
					[
						96562.5,
						2,
						0,
						""
					],
					[
						96937.5,
						9,
						0,
						""
					],
					[
						97312.5,
						0,
						0,
						""
					],
					[
						97406.25,
						3,
						0,
						""
					],
					[
						97500,
						7,
						0,
						""
					],
					[
						97687.5,
						4,
						0,
						""
					],
					[
						97875,
						8,
						0,
						""
					],
					[
						98062.5,
						2,
						0,
						""
					],
					[
						96562.5,
						8,
						0,
						""
					],
					[
						96937.5,
						3,
						0,
						""
					],
					[
						97312.5,
						4,
						0,
						""
					],
					[
						97406.25,
						9,
						0,
						""
					],
					[
						97500,
						1,
						0,
						""
					],
					[
						97687.5,
						0,
						0,
						""
					],
					[
						97875,
						2,
						0,
						""
					],
					[
						98062.5,
						6,
						0,
						""
					]
				],
				"gfSection": false,
				"denominator": 4,
				"changeBPM": false,
				"bpm": 160
			},
			{
				"changeSignature": false,
				"numerator": 5,
				"altAnim": false,
				"mustHitSection": true,
				"lengthInSteps": 36,
				"typeOfSection": 0,
				"sectionNotes": [
					[
						98250,
						1,
						0,
						""
					],
					[
						98625,
						6,
						0,
						""
					],
					[
						99000,
						7,
						0,
						""
					],
					[
						99187.5,
						2,
						0,
						""
					],
					[
						99093.75,
						0,
						0,
						""
					],
					[
						99375,
						5,
						0,
						""
					],
					[
						99750,
						3,
						0,
						""
					],
					[
						99562.5,
						4,
						0,
						""
					]
				],
				"gfSection": false,
				"denominator": 4,
				"changeBPM": false,
				"bpm": 160
			},
			{
				"changeSignature": false,
				"numerator": 5,
				"altAnim": false,
				"mustHitSection": true,
				"lengthInSteps": 36,
				"typeOfSection": 0,
				"sectionNotes": [
					[
						99937.5,
						5,
						0,
						""
					],
					[
						100312.5,
						6,
						0,
						""
					],
					[
						100687.5,
						7,
						0,
						""
					],
					[
						100875,
						0,
						0,
						""
					],
					[
						100781.25,
						3,
						0,
						""
					],
					[
						101062.5,
						6,
						0,
						""
					],
					[
						101437.5,
						1,
						0,
						""
					],
					[
						101250,
						2,
						0,
						""
					]
				],
				"gfSection": false,
				"denominator": 4,
				"changeBPM": false,
				"bpm": 160
			},
			{
				"changeSignature": false,
				"numerator": 5,
				"altAnim": false,
				"mustHitSection": true,
				"lengthInSteps": 36,
				"typeOfSection": 0,
				"sectionNotes": [
					[
						101625,
						1,
						0,
						""
					],
					[
						102000,
						6,
						0,
						""
					],
					[
						102375,
						7,
						0,
						""
					],
					[
						102562.5,
						2,
						0,
						""
					],
					[
						102468.75,
						0,
						0,
						""
					],
					[
						102750,
						5,
						0,
						""
					],
					[
						103125,
						3,
						0,
						""
					],
					[
						102937.5,
						4,
						0,
						""
					],
					[
						101625,
						5,
						0,
						""
					],
					[
						102000,
						2,
						0,
						""
					],
					[
						102375,
						3,
						0,
						""
					],
					[
						102468.75,
						4,
						0,
						""
					],
					[
						102562.5,
						6,
						0,
						""
					],
					[
						102750,
						1,
						0,
						""
					],
					[
						102937.5,
						3,
						0,
						""
					],
					[
						103125,
						7,
						0,
						""
					]
				],
				"gfSection": false,
				"denominator": 4,
				"changeBPM": false,
				"bpm": 160
			},
			{
				"changeSignature": false,
				"numerator": 5,
				"altAnim": false,
				"mustHitSection": true,
				"lengthInSteps": 36,
				"typeOfSection": 0,
				"sectionNotes": [
					[
						103312.5,
						5,
						0,
						""
					],
					[
						103687.5,
						6,
						0,
						""
					],
					[
						104062.5,
						7,
						0,
						""
					],
					[
						104250,
						0,
						0,
						""
					],
					[
						104156.25,
						3,
						0,
						""
					],
					[
						104437.5,
						6,
						0,
						""
					],
					[
						104812.5,
						1,
						0,
						""
					],
					[
						104625,
						2,
						0,
						""
					],
					[
						103312.5,
						1,
						0,
						""
					],
					[
						103687.5,
						1,
						0,
						""
					],
					[
						104062.5,
						0,
						0,
						""
					],
					[
						104156.25,
						6,
						0,
						""
					],
					[
						104250,
						4,
						0,
						""
					],
					[
						104437.5,
						1,
						0,
						""
					],
					[
						104625,
						7,
						0,
						""
					],
					[
						104812.5,
						5,
						0,
						""
					]
				],
				"gfSection": false,
				"denominator": 4,
				"changeBPM": false,
				"bpm": 160
			},
			{
				"changeSignature": true,
				"numerator": 7,
				"altAnim": false,
				"mustHitSection": false,
				"lengthInSteps": 28,
				"typeOfSection": 0,
				"sectionNotes": [
					[
						105000,
						2,
						0,
						""
					],
					[
						105093.75,
						5,
						0,
						""
					],
					[
						105187.5,
						1,
						0,
						""
					],
					[
						105375,
						6,
						0,
						""
					],
					[
						105562.5,
						8,
						0,
						""
					],
					[
						105750,
						1,
						0,
						""
					],
					[
						105843.75,
						1,
						0,
						""
					],
					[
						105937.5,
						4,
						0,
						""
					],
					[
						106125,
						7,
						0,
						""
					],
					[
						106312.5,
						8,
						0,
						""
					],
					[
						106500,
						0,
						0,
						""
					],
					[
						106687.5,
						5,
						0,
						""
					],
					[
						106781.25,
						6,
						0,
						""
					],
					[
						106875,
						8,
						0,
						""
					],
					[
						107062.5,
						2,
						0,
						""
					],
					[
						107250,
						1,
						0,
						""
					],
					[
						107343.75,
						8,
						0,
						""
					],
					[
						107437.5,
						9,
						0,
						""
					]
				],
				"gfSection": false,
				"denominator": 4,
				"changeBPM": false,
				"bpm": 160
			},
			{
				"changeSignature": false,
				"numerator": 5,
				"altAnim": false,
				"mustHitSection": false,
				"lengthInSteps": 28,
				"typeOfSection": 0,
				"sectionNotes": [
					[
						107625,
						2,
						0,
						""
					],
					[
						107718.75,
						5,
						0,
						""
					],
					[
						107812.5,
						1,
						0,
						""
					],
					[
						108000,
						6,
						0,
						""
					],
					[
						108187.5,
						8,
						0,
						""
					],
					[
						108375,
						1,
						0,
						""
					],
					[
						108468.75,
						1,
						0,
						""
					],
					[
						108562.5,
						4,
						0,
						""
					],
					[
						108750,
						7,
						0,
						""
					],
					[
						108937.5,
						8,
						0,
						""
					],
					[
						109125,
						4,
						0,
						""
					],
					[
						109218.75,
						7,
						0,
						""
					],
					[
						109406.25,
						1,
						0,
						""
					],
					[
						109312.5,
						2,
						0,
						""
					],
					[
						109500,
						9,
						0,
						""
					],
					[
						109593.75,
						8,
						0,
						""
					],
					[
						109687.5,
						0,
						0,
						""
					],
					[
						109781.25,
						1,
						0,
						""
					],
					[
						109875,
						7,
						0,
						""
					],
					[
						110062.5,
						9,
						0,
						""
					]
				],
				"gfSection": false,
				"denominator": 4,
				"changeBPM": false,
				"bpm": 160
			},
			{
				"changeSignature": false,
				"numerator": 5,
				"altAnim": false,
				"mustHitSection": true,
				"lengthInSteps": 28,
				"typeOfSection": 0,
				"sectionNotes": [
					[
						110250,
						10,
						0,
						""
					],
					[
						110343.75,
						13,
						0,
						""
					],
					[
						110437.5,
						9,
						0,
						""
					],
					[
						110625,
						14,
						0,
						""
					],
					[
						110812.5,
						16,
						0,
						""
					],
					[
						111000,
						9,
						0,
						""
					],
					[
						111093.75,
						9,
						0,
						""
					],
					[
						111187.5,
						12,
						0,
						""
					],
					[
						111375,
						15,
						0,
						""
					],
					[
						111562.5,
						16,
						0,
						""
					],
					[
						111750,
						12,
						0,
						""
					],
					[
						111843.75,
						15,
						0,
						""
					],
					[
						112031.25,
						9,
						0,
						""
					],
					[
						111937.5,
						10,
						0,
						""
					],
					[
						112125,
						17,
						0,
						""
					],
					[
						112218.75,
						16,
						0,
						""
					],
					[
						112312.5,
						8,
						0,
						""
					],
					[
						112406.25,
						9,
						0,
						""
					],
					[
						112500,
						15,
						0,
						""
					],
					[
						112687.5,
						17,
						0,
						""
					],
					[
						110250,
						1,
						1406.25,
						""
					],
					[
						111750,
						5,
						468.75,
						""
					],
					[
						112312.5,
						7,
						468.75,
						""
					]
				],
				"gfSection": false,
				"denominator": 4,
				"changeBPM": false,
				"bpm": 160
			},
			{
				"changeSignature": false,
				"numerator": 5,
				"altAnim": false,
				"mustHitSection": false,
				"lengthInSteps": 28,
				"typeOfSection": 0,
				"sectionNotes": [
					[
						112875,
						14,
						1406.25,
						""
					],
					[
						114375,
						16,
						468.75,
						""
					],
					[
						114937.5,
						11,
						468.75,
						""
					],
					[
						112875,
						5,
						0,
						""
					],
					[
						113250,
						5,
						0,
						""
					],
					[
						113437.5,
						8,
						0,
						""
					],
					[
						113812.5,
						2,
						0,
						""
					],
					[
						114000,
						4,
						0,
						""
					],
					[
						114187.5,
						9,
						0,
						""
					],
					[
						114375,
						6,
						0,
						""
					],
					[
						114562.5,
						7,
						0,
						""
					],
					[
						114750,
						3,
						0,
						""
					],
					[
						114937.5,
						3,
						0,
						""
					],
					[
						115125,
						7,
						0,
						""
					],
					[
						115312.5,
						9,
						0,
						""
					]
				],
				"gfSection": false,
				"denominator": 4,
				"changeBPM": false,
				"bpm": 160
			},
			{
				"changeSignature": false,
				"numerator": 5,
				"altAnim": false,
				"mustHitSection": true,
				"lengthInSteps": 28,
				"typeOfSection": 0,
				"sectionNotes": [
					[
						115500,
						2,
						0,
						""
					],
					[
						115593.75,
						3,
						0,
						""
					],
					[
						115687.5,
						5,
						0,
						""
					],
					[
						115875,
						1,
						0,
						""
					],
					[
						116062.5,
						6,
						0,
						""
					],
					[
						116250,
						7,
						0,
						""
					],
					[
						116343.75,
						7,
						0,
						""
					],
					[
						116437.5,
						0,
						0,
						""
					],
					[
						116625,
						1,
						0,
						""
					],
					[
						116812.5,
						6,
						0,
						""
					],
					[
						117000,
						3,
						0,
						""
					],
					[
						117187.5,
						4,
						0,
						""
					],
					[
						117281.25,
						5,
						0,
						""
					],
					[
						117375,
						2,
						0,
						""
					],
					[
						117562.5,
						3,
						0,
						""
					],
					[
						117750,
						1,
						0,
						""
					],
					[
						117843.75,
						7,
						0,
						""
					],
					[
						117937.5,
						6,
						0,
						""
					]
				],
				"gfSection": false,
				"denominator": 4,
				"changeBPM": false,
				"bpm": 160
			},
			{
				"changeSignature": false,
				"numerator": 5,
				"altAnim": false,
				"mustHitSection": true,
				"lengthInSteps": 28,
				"typeOfSection": 0,
				"sectionNotes": [
					[
						118125,
						2,
						0,
						""
					],
					[
						118218.75,
						3,
						0,
						""
					],
					[
						118312.5,
						1,
						0,
						""
					],
					[
						118500,
						4,
						0,
						""
					],
					[
						118687.5,
						7,
						0,
						""
					],
					[
						118875,
						1,
						0,
						""
					],
					[
						118968.75,
						1,
						0,
						""
					],
					[
						119062.5,
						6,
						0,
						""
					],
					[
						119250,
						5,
						0,
						""
					],
					[
						119437.5,
						2,
						0,
						""
					],
					[
						119718.75,
						7,
						0,
						""
					],
					[
						119625,
						7,
						0,
						""
					],
					[
						119812.5,
						0,
						0,
						""
					],
					[
						119906.25,
						0,
						0,
						""
					],
					[
						120000,
						6,
						0,
						""
					],
					[
						120093.75,
						6,
						0,
						""
					],
					[
						120187.5,
						3,
						0,
						""
					],
					[
						120281.25,
						3,
						0,
						""
					],
					[
						120375,
						5,
						0,
						""
					],
					[
						120562.5,
						7,
						0,
						""
					]
				],
				"gfSection": false,
				"denominator": 4,
				"changeBPM": false,
				"bpm": 160
			},
			{
				"changeSignature": false,
				"numerator": 5,
				"altAnim": false,
				"mustHitSection": false,
				"lengthInSteps": 28,
				"typeOfSection": 0,
				"sectionNotes": [
					[
						120750,
						12,
						0,
						""
					],
					[
						120843.75,
						13,
						0,
						""
					],
					[
						120937.5,
						14,
						0,
						""
					],
					[
						121125,
						11,
						0,
						""
					],
					[
						121312.5,
						16,
						0,
						""
					],
					[
						121500,
						13,
						0,
						""
					],
					[
						121593.75,
						13,
						0,
						""
					],
					[
						121687.5,
						14,
						0,
						""
					],
					[
						121875,
						15,
						0,
						""
					],
					[
						122062.5,
						12,
						0,
						""
					],
					[
						122250,
						11,
						0,
						""
					],
					[
						122437.5,
						16,
						0,
						""
					],
					[
						122531.25,
						17,
						0,
						""
					],
					[
						122625,
						16,
						0,
						""
					],
					[
						122812.5,
						10,
						0,
						""
					],
					[
						123000,
						11,
						0,
						""
					],
					[
						123093.75,
						12,
						0,
						""
					],
					[
						123187.5,
						17,
						0,
						""
					],
					[
						120750,
						4,
						1406.25,
						""
					],
					[
						122250,
						7,
						468.75,
						""
					],
					[
						122812.5,
						9,
						468.75,
						""
					]
				],
				"gfSection": false,
				"denominator": 4,
				"changeBPM": false,
				"bpm": 160
			},
			{
				"changeSignature": false,
				"numerator": 5,
				"altAnim": false,
				"mustHitSection": false,
				"lengthInSteps": 28,
				"typeOfSection": 0,
				"sectionNotes": [
					[
						123375,
						7,
						1406.25,
						""
					],
					[
						124875,
						2,
						468.75,
						""
					],
					[
						125437.5,
						0,
						468.75,
						""
					],
					[
						123375,
						11,
						0,
						""
					],
					[
						123750,
						15,
						0,
						""
					],
					[
						123937.5,
						12,
						0,
						""
					],
					[
						124312.5,
						14,
						0,
						""
					],
					[
						124500,
						17,
						0,
						""
					],
					[
						124687.5,
						10,
						0,
						""
					],
					[
						124875,
						16,
						0,
						""
					],
					[
						125062.5,
						11,
						0,
						""
					],
					[
						125250,
						15,
						0,
						""
					],
					[
						125437.5,
						17,
						0,
						""
					],
					[
						125625,
						14,
						0,
						""
					],
					[
						125812.5,
						11,
						0,
						""
					],
					[
						125906.25,
						13,
						0,
						""
					]
				],
				"gfSection": false,
				"denominator": 4,
				"changeBPM": false,
				"bpm": 160
			},
			{
				"changeSignature": false,
				"numerator": 5,
				"altAnim": false,
				"mustHitSection": true,
				"lengthInSteps": 28,
				"typeOfSection": 0,
				"sectionNotes": [
					[
						126000,
						6,
						1968.75,
						""
					],
					[
						126000,
						10,
						1406.25,
						""
					]
				],
				"gfSection": false,
				"denominator": 4,
				"changeBPM": false,
				"bpm": 160
			},
			{
				"changeSignature": false,
				"numerator": 5,
				"altAnim": false,
				"mustHitSection": true,
				"lengthInSteps": 28,
				"typeOfSection": 0,
				"sectionNotes": [],
				"gfSection": false,
				"denominator": 4,
				"changeBPM": false,
				"bpm": 160
			},
			{
				"changeSignature": false,
				"numerator": 5,
				"altAnim": false,
				"mustHitSection": true,
				"lengthInSteps": 28,
				"typeOfSection": 0,
				"sectionNotes": [],
				"gfSection": false,
				"denominator": 4,
				"changeBPM": false,
				"bpm": 160
			},
			{
				"changeSignature": false,
				"numerator": 5,
				"altAnim": false,
				"mustHitSection": true,
				"lengthInSteps": 28,
				"typeOfSection": 0,
				"sectionNotes": [],
				"gfSection": false,
				"denominator": 4,
				"changeBPM": false,
				"bpm": 160
			},
			{
				"changeSignature": false,
				"numerator": 5,
				"altAnim": false,
				"mustHitSection": true,
				"lengthInSteps": 28,
				"typeOfSection": 0,
				"sectionNotes": [],
				"denominator": 4,
				"gfSection": false,
				"bpm": 160,
				"changeBPM": false
			},
			{
				"changeSignature": false,
				"numerator": 5,
				"altAnim": false,
				"mustHitSection": true,
				"lengthInSteps": 28,
				"typeOfSection": 0,
				"sectionNotes": [],
				"gfSection": false,
				"denominator": 4,
				"changeBPM": false,
				"bpm": 160
			},
			{
				"changeSignature": false,
				"numerator": 5,
				"altAnim": false,
				"mustHitSection": true,
				"lengthInSteps": 28,
				"typeOfSection": 0,
				"sectionNotes": [],
				"gfSection": false,
				"denominator": 4,
				"changeBPM": false,
				"bpm": 160
			},
			{
				"changeSignature": false,
				"numerator": 5,
				"altAnim": false,
				"mustHitSection": true,
				"lengthInSteps": 28,
				"typeOfSection": 0,
				"sectionNotes": [],
				"gfSection": false,
				"denominator": 4,
				"changeBPM": false,
				"bpm": 160
			},
			{
				"changeSignature": false,
				"numerator": 5,
				"altAnim": false,
				"mustHitSection": true,
				"lengthInSteps": 28,
				"typeOfSection": 0,
				"sectionNotes": [],
				"gfSection": false,
				"denominator": 4,
				"changeBPM": false,
				"bpm": 160
			},
			{
				"changeSignature": false,
				"numerator": 5,
				"altAnim": false,
				"mustHitSection": true,
				"lengthInSteps": 28,
				"typeOfSection": 0,
				"sectionNotes": [],
				"denominator": 4,
				"gfSection": false,
				"bpm": 160,
				"changeBPM": false
			},
			{
				"changeSignature": false,
				"numerator": 5,
				"altAnim": false,
				"mustHitSection": true,
				"lengthInSteps": 28,
				"typeOfSection": 0,
				"sectionNotes": [],
				"gfSection": false,
				"denominator": 4,
				"changeBPM": false,
				"bpm": 160
			},
			{
				"numerator": 5,
				"changeSignature": false,
				"gfSection": false,
				"lengthInSteps": 28,
				"altAnim": false,
				"denominator": 4,
				"typeOfSection": 0,
				"sectionNotes": [],
				"bpm": 160,
				"changeBPM": false,
				"mustHitSection": true
			}
		],
		"player2": "dad",
		"song": "Calamitous Timelines",
		"playerKeyAmount": 8,
		"denominator": 4,
		"validScore": true,
		"speed": 1.8,
		"events": [
			[
				22000,
				[
					[
						"Change Scroll Speed",
						"1.333333333",
						"0.5"
					]
				]
			],
			[
				24187.5,
				[
					[
						"Add Camera Zoom",
						"",
						""
					]
				]
			],
			[
				24562.5,
				[
					[
						"Add Camera Zoom",
						"",
						""
					]
				]
			],
			[
				24750,
				[
					[
						"Add Camera Zoom",
						"",
						""
					]
				]
			],
			[
				26812.5,
				[
					[
						"Add Camera Zoom",
						"",
						""
					]
				]
			],
			[
				27187.5,
				[
					[
						"Add Camera Zoom",
						"",
						""
					]
				]
			],
			[
				27375,
				[
					[
						"Add Camera Zoom",
						"",
						""
					]
				]
			],
			[
				29437.5,
				[
					[
						"Add Camera Zoom",
						"",
						""
					]
				]
			],
			[
				29812.5,
				[
					[
						"Add Camera Zoom",
						"",
						""
					]
				]
			],
			[
				30000,
				[
					[
						"Add Camera Zoom",
						"",
						""
					]
				]
			],
			[
				32062.5,
				[
					[
						"Add Camera Zoom",
						"",
						""
					]
				]
			],
			[
				32437.5,
				[
					[
						"Add Camera Zoom",
						"",
						""
					]
				]
			],
			[
				32625,
				[
					[
						"Add Camera Zoom",
						"",
						""
					]
				]
			],
			[
				34687.5,
				[
					[
						"Add Camera Zoom",
						"",
						""
					]
				]
			],
			[
				35062.5,
				[
					[
						"Add Camera Zoom",
						"",
						""
					]
				]
			],
			[
				35250,
				[
					[
						"Add Camera Zoom",
						"",
						""
					]
				]
			],
			[
				37312.5,
				[
					[
						"Add Camera Zoom",
						"",
						""
					]
				]
			],
			[
				37687.5,
				[
					[
						"Add Camera Zoom",
						"",
						""
					]
				]
			],
			[
				37875,
				[
					[
						"Add Camera Zoom",
						"",
						""
					]
				]
			],
			[
				39937.5,
				[
					[
						"Add Camera Zoom",
						"",
						""
					]
				]
			],
			[
				40312.5,
				[
					[
						"Add Camera Zoom",
						"",
						""
					]
				]
			],
			[
				40500,
				[
					[
						"Add Camera Zoom",
						"",
						""
					]
				]
			],
			[
				42562.5,
				[
					[
						"Add Camera Zoom",
						"",
						""
					]
				]
			],
			[
				42937.5,
				[
					[
						"Add Camera Zoom",
						"",
						""
					]
				]
			],
			[
				43125,
				[
					[
						"Add Camera Zoom",
						"",
						""
					]
				]
			],
			[
				45000,
				[
					[
						"Add Camera Zoom",
						"",
						""
					]
				]
			],
			[
				45375,
				[
					[
						"Add Camera Zoom",
						"",
						""
					]
				]
			],
			[
				47062.5,
				[
					[
						"Add Camera Zoom",
						"",
						""
					]
				]
			],
			[
				47437.5,
				[
					[
						"Add Camera Zoom",
						"",
						""
					]
				]
			],
			[
				49125,
				[
					[
						"Add Camera Zoom",
						"",
						""
					]
				]
			],
			[
				49500,
				[
					[
						"Add Camera Zoom",
						"",
						""
					]
				]
			],
			[
				51187.5,
				[
					[
						"Add Camera Zoom",
						"",
						""
					]
				]
			],
			[
				51562.5,
				[
					[
						"Add Camera Zoom",
						"",
						""
					]
				]
			],
			[
				53250,
				[
					[
						"Add Camera Zoom",
						"",
						""
					]
				]
			],
			[
				53625,
				[
					[
						"Add Camera Zoom",
						"",
						""
					]
				]
			],
			[
				55312.5,
				[
					[
						"Add Camera Zoom",
						"",
						""
					]
				]
			],
			[
				55687.5,
				[
					[
						"Add Camera Zoom",
						"",
						""
					]
				]
			],
			[
				57375,
				[
					[
						"Add Camera Zoom",
						"",
						""
					]
				]
			],
			[
				57750,
				[
					[
						"Add Camera Zoom",
						"",
						""
					]
				]
			],
			[
				59437.5,
				[
					[
						"Add Camera Zoom",
						"",
						""
					]
				]
			],
			[
				59812.5,
				[
					[
						"Add Camera Zoom",
						"",
						""
					]
				]
			],
			[
				63937.5,
				[
					[
						"Add Camera Zoom",
						"",
						""
					]
				]
			],
			[
				68437.5,
				[
					[
						"Add Camera Zoom",
						"",
						""
					]
				]
			],
			[
				72937.5,
				[
					[
						"Add Camera Zoom",
						"",
						""
					]
				]
			],
			[
				77437.5,
				[
					[
						"Add Camera Zoom",
						"",
						""
					]
				]
			],
			[
				79500,
				[
					[
						"Add Camera Zoom",
						"",
						""
					]
				]
			],
			[
				81187.5,
				[
					[
						"Add Camera Zoom",
						"",
						""
					]
				]
			],
			[
				82875,
				[
					[
						"Add Camera Zoom",
						"",
						""
					]
				]
			],
			[
				84562.5,
				[
					[
						"Add Camera Zoom",
						"",
						""
					]
				]
			],
			[
				86250,
				[
					[
						"Add Camera Zoom",
						"",
						""
					]
				]
			],
			[
				87937.5,
				[
					[
						"Add Camera Zoom",
						"",
						""
					]
				]
			],
			[
				89625,
				[
					[
						"Add Camera Zoom",
						"",
						""
					]
				]
			],
			[
				91312.5,
				[
					[
						"Add Camera Zoom",
						"",
						""
					]
				]
			],
			[
				93000,
				[
					[
						"Add Camera Zoom",
						"",
						""
					]
				]
			],
			[
				94687.5,
				[
					[
						"Add Camera Zoom",
						"",
						""
					]
				]
			],
			[
				96375,
				[
					[
						"Add Camera Zoom",
						"",
						""
					]
				]
			],
			[
				98062.5,
				[
					[
						"Add Camera Zoom",
						"",
						""
					]
				]
			],
			[
				99750,
				[
					[
						"Add Camera Zoom",
						"",
						""
					]
				]
			],
			[
				101437.5,
				[
					[
						"Add Camera Zoom",
						"",
						""
					]
				]
			],
			[
				103125,
				[
					[
						"Add Camera Zoom",
						"",
						""
					]
				]
			],
			[
				104500,
				[
					[
						"Change Scroll Speed",
						"1.333333333",
						"0.5"
					]
				]
			],
			[
				104812.5,
				[
					[
						"Add Camera Zoom",
						"",
						""
					]
				]
			],
			[
				106687.5,
				[
					[
						"Add Camera Zoom",
						"",
						""
					]
				]
			],
			[
				107062.5,
				[
					[
						"Add Camera Zoom",
						"",
						""
					]
				]
			],
			[
				107250,
				[
					[
						"Add Camera Zoom",
						"",
						""
					]
				]
			],
			[
				109312.5,
				[
					[
						"Add Camera Zoom",
						"",
						""
					]
				]
			],
			[
				109687.5,
				[
					[
						"Add Camera Zoom",
						"",
						""
					]
				]
			],
			[
				109875,
				[
					[
						"Add Camera Zoom",
						"",
						""
					]
				]
			],
			[
				111937.5,
				[
					[
						"Add Camera Zoom",
						"",
						""
					]
				]
			],
			[
				112312.5,
				[
					[
						"Add Camera Zoom",
						"",
						""
					]
				]
			],
			[
				112500,
				[
					[
						"Add Camera Zoom",
						"",
						""
					]
				]
			],
			[
				114562.5,
				[
					[
						"Add Camera Zoom",
						"",
						""
					]
				]
			],
			[
				114937.5,
				[
					[
						"Add Camera Zoom",
						"",
						""
					]
				]
			],
			[
				115125,
				[
					[
						"Add Camera Zoom",
						"",
						""
					]
				]
			],
			[
				117187.5,
				[
					[
						"Add Camera Zoom",
						"",
						""
					]
				]
			],
			[
				117562.5,
				[
					[
						"Add Camera Zoom",
						"",
						""
					]
				]
			],
			[
				117750,
				[
					[
						"Add Camera Zoom",
						"",
						""
					]
				]
			],
			[
				119812.5,
				[
					[
						"Add Camera Zoom",
						"",
						""
					]
				]
			],
			[
				120187.5,
				[
					[
						"Add Camera Zoom",
						"",
						""
					]
				]
			],
			[
				120375,
				[
					[
						"Add Camera Zoom",
						"",
						""
					]
				]
			],
			[
				122437.5,
				[
					[
						"Add Camera Zoom",
						"",
						""
					]
				]
			],
			[
				122812.5,
				[
					[
						"Add Camera Zoom",
						"",
						""
					]
				]
			],
			[
				123000,
				[
					[
						"Add Camera Zoom",
						"",
						""
					]
				]
			],
			[
				125062.5,
				[
					[
						"Add Camera Zoom",
						"",
						""
					]
				]
			],
			[
				125437.5,
				[
					[
						"Add Camera Zoom",
						"",
						""
					]
				]
			],
			[
				125625,
				[
					[
						"Add Camera Zoom",
						"",
						""
					]
				]
			]
		],
		"numerator": 5,
		"gfVersion": "gf",
		"opponentKeyAmount": 10,
		"stage": "stage",
		"needsVoices": true,
		"uiSkinOpponent": "",
		"bpm": 160
	}
}